[
    {
        "Numero":1,
        "Nombre":"bulbasur",
        "Tipo":"Planta",
        "Imagen":"https://raw.githubusercontent.com/PokeAPI/sprites/master/sprites/pokemon/back/shiny/132.png",
        "Ataque":"Latigo Cepa"
    },
    {
        "Numero":2,
        "Nombre":"Snivy",
        "Tipo":"Planta",
        "Imagen":"https://raw.githubusercontent.com/PokeAPI/sprites/master/sprites/pokemon/back/shiny/495.png",
        "Ataque":"slam"
    },
    {
        "Numero":3,
        "Nombre":"Deerling",
        "Tipo":"Planta",
        "Imagen":"https://raw.githubusercontent.com/PokeAPI/sprites/master/sprites/pokemon/back/shiny/585.png",
        "Ataque":"substitute"
    },
    {
        "Numero":4,
        "Nombre":"Amoonguss",
        "Tipo":"Planta",
        "Imagen":"https://raw.githubusercontent.com/PokeAPI/sprites/master/sprites/pokemon/back/shiny/591.png",
        "Ataque":"solar-beam"
    },
    {
        "Numero":5,
        "Nombre":"Virizion",
        "Tipo":"Planta",
        "Imagen":"https://raw.githubusercontent.com/PokeAPI/sprites/master/sprites/pokemon/back/shiny/640.png",
        "Ataque":"toxic"
    },
    {
        "Numero":6,
        "Nombre":"Darumaka",
        "Tipo":"Fuego",
        "Imagen":"https://raw.githubusercontent.com/PokeAPI/sprites/master/sprites/pokemon/back/shiny/554.png",
        "Ataque":"fire-punch"
    },
    {
        "Numero":7,
        "Nombre":"Volcarona",
        "Tipo":"Fuego",
        "Imagen":"https://raw.githubusercontent.com/PokeAPI/sprites/master/sprites/pokemon/back/shiny/637.png",
        "Ataque":"flamethrower"
    },
    {
        "Numero":8,
        "Nombre":"Heatran",
        "Tipo":"Fuego",
        "Imagen":"https://raw.githubusercontent.com/PokeAPI/sprites/master/sprites/pokemon/back/shiny/485.png",
        "Ataque":"ancient-power"
    },
    {
        "Numero":9,
        "Nombre":"Charmander",
        "Tipo":"Fuego",
        "Imagen":"https://raw.githubusercontent.com/PokeAPI/sprites/master/sprites/pokemon/back/shiny/4.png",
        "Ataque":"fire-blast"
    },
    {
        "Numero":10,
        "Nombre":"Emboar",
        "Tipo":"Fuego",
        "Imagen":"https://raw.githubusercontent.com/PokeAPI/sprites/master/sprites/pokemon/back/shiny/500.png",
        "Ataque":"sunny-day"
    },
    {
        "Numero":11,
        "Nombre":"Samurott",
        "Tipo":"Agua",
        "Imagen":"https://raw.githubusercontent.com/PokeAPI/sprites/master/sprites/pokemon/back/shiny/503.png",
        "Ataque":"Surf"
    },
    {
        "Numero":12,
        "Nombre":"Golduck",
        "Tipo":"Agua",
        "Imagen":"https://raw.githubusercontent.com/PokeAPI/sprites/master/sprites/pokemon/back/shiny/55.png",
        "Ataque":"ice-punch"
    },
    {
        "Numero":13,
        "Nombre":"Pelipper",
        "Tipo":"Agua",
        "Imagen":"https://raw.githubusercontent.com/PokeAPI/sprites/master/sprites/pokemon/back/shiny/279.png",
        "Ataque":"fly"
    },
    {
        "Numero":14,
        "Nombre":"Lapras",
        "Tipo":"Agua",
        "Imagen":"https://raw.githubusercontent.com/PokeAPI/sprites/master/sprites/pokemon/back/shiny/131.png",
        "Ataque":"headbutt"
    },
    {
        "Numero":15,
        "Nombre":"Marill",
        "Tipo":"Agua",
        "Imagen":"https://raw.githubusercontent.com/PokeAPI/sprites/master/sprites/pokemon/back/shiny/183.png",
        "Ataque":"water-gun"
    }
]